AUTHORS.rst
CONTRIBUTING.rst
HISTORY.rst
LICENSE
MANIFEST.in
README.rst
setup.cfg
setup.py
ansible/__init__.py
ansible/module_utils/__init__.py
ansible/module_utils/_text.py
ansible/module_utils/basic.py
ansible/module_utils/errors.py
ansible/module_utils/pycompat24.py
ansible/module_utils/urls.py
ansible/module_utils/common/__init__.py
ansible/module_utils/common/_collections_compat.py
ansible/module_utils/common/_json_compat.py
ansible/module_utils/common/_utils.py
ansible/module_utils/common/arg_spec.py
ansible/module_utils/common/collections.py
ansible/module_utils/common/file.py
ansible/module_utils/common/locale.py
ansible/module_utils/common/parameters.py
ansible/module_utils/common/process.py
ansible/module_utils/common/sys_info.py
ansible/module_utils/common/validation.py
ansible/module_utils/common/warnings.py
ansible/module_utils/common/text/__init__.py
ansible/module_utils/common/text/converters.py
ansible/module_utils/common/text/formatters.py
ansible/module_utils/compat/__init__.py
ansible/module_utils/compat/selectors.py
ansible/module_utils/distro/__init__.py
ansible/module_utils/parsing/__init__.py
ansible/module_utils/parsing/convert_bool.py
ansible/module_utils/six/__init__.py
docs/Makefile
docs/authors.rst
docs/conf.py
docs/contributing.rst
docs/history.rst
docs/index.rst
docs/installation.rst
docs/make.bat
docs/readme.rst
docs/usage.rst
ftl_module_utils/__init__.py
ftl_module_utils/ftl_module_utils.py
ftl_module_utils/load.py
ftl_module_utils.egg-info/PKG-INFO
ftl_module_utils.egg-info/SOURCES.txt
ftl_module_utils.egg-info/dependency_links.txt
ftl_module_utils.egg-info/not-zip-safe
ftl_module_utils.egg-info/top_level.txt
ftl_module_utils/module_utils/__init__.py
ftl_module_utils/module_utils/_text.py
ftl_module_utils/module_utils/basic.py
ftl_module_utils/module_utils/errors.py
ftl_module_utils/module_utils/pycompat24.py
ftl_module_utils/module_utils/urls.py
ftl_module_utils/module_utils/common/__init__.py
ftl_module_utils/module_utils/common/_collections_compat.py
ftl_module_utils/module_utils/common/_json_compat.py
ftl_module_utils/module_utils/common/_utils.py
ftl_module_utils/module_utils/common/arg_spec.py
