Metadata-Version: 2.1
Name: ftl-module-utils
Version: 0.1.0
Summary: Module utils for Faster Than Light
Home-page: https://github.com/benthomasson/ftl_module_utils
Author: Ben Thomasson
Author-email: ben.thomasson@gmail.com
License: BSD license
Keywords: ftl_module_utils
Platform: UNKNOWN
Classifier: Development Status :: 2 - Pre-Alpha
Classifier: Intended Audience :: Developers
Classifier: License :: OSI Approved :: BSD License
Classifier: Natural Language :: English
Classifier: Programming Language :: Python :: 3
Classifier: Programming Language :: Python :: 3.6
Classifier: Programming Language :: Python :: 3.7
Classifier: Programming Language :: Python :: 3.8
Requires-Python: >=3.6
License-File: LICENSE
License-File: AUTHORS.rst
